msteams/__init__.py
msteams/adaptivecard/__init__.py
msteams/adaptivecard/card.py
msteams/adaptivecard/containers/__init__.py
msteams/adaptivecard/containers/column.py
msteams/adaptivecard/containers/column_set.py
msteams/adaptivecard/containers/container.py
msteams/adaptivecard/containers/fact.py
msteams/adaptivecard/containers/fact_set.py
msteams/adaptivecard/containers/layout.py
msteams/adaptivecard/elements/__init__.py
msteams/adaptivecard/elements/element.py
msteams/adaptivecard/elements/image.py
msteams/adaptivecard/elements/text_block.py
msteams/messagecard/__init__.py
msteams/messagecard/card.py
msteams/messagecard/fact.py
msteams/messagecard/section.py
ms_teams-0.1.0.dist-info/LICENSE
ms_teams-0.1.0.dist-info/METADATA
ms_teams-0.1.0.dist-info/WHEEL
ms_teams-0.1.0.dist-info/top_level.txt
ms_teams-0.1.0.dist-info/RECORD
