Metadata-Version: 2.1
Name: ms-teams
Version: 0.1.0
Summary: Helper library to construct microsoft teams connector cards
Home-page: https://github.com/HarshadRanganathan/ms-teams
Author: Harshad Ranganathan
Author-email: rharshad93@gmail.com
License: MIT
Keywords: Microsoft Teams
Platform: UNKNOWN
Classifier: Programming Language :: Python :: 3.7
Classifier: License :: OSI Approved :: MIT License
Classifier: Operating System :: OS Independent
Classifier: Intended Audience :: Developers
Classifier: Topic :: Software Development :: Libraries :: Python Modules
Requires-Python: >=3.7
Requires-Dist: jsonpickle
